{
  "_schema": "2.0",
  "_last_updated": "2026-04-11T20:03:17.828866+00:00",
  "_clinic_path": "THE_CLINIC/translation-pairs/ALMA-13B-R.json",
  "patient_id": "ALMA-13B-R",
  "admitted": "2026-03-24T08:31:42.801810",
  "source_repo": "Helsinki-NLP/opus-mt-ALMA-13B-R",
  "source_language": {
    "code": "ALMA",
    "name": "ALMA",
    "family": "Unknown"
  },
  "target_language": {
    "code": "R",
    "name": "R",
    "family": "Unknown"
  },
  "variant_cluster": {
    "base": {
      "status": "missing_from_disk",
      "note": "Weights not found on disk. May have been deleted, renamed, or archived as ONNX (see variant_cluster.onnx_int8_archive if present).",
      "reconciled_at": "2026-04-11T20:03:17.828866+00:00",
      "reconciled_by": "Opus 4.6 Opus-Claw (Dr. C)"
    },
    "lora": {
      "status": "missing_from_disk",
      "note": "Weights not found on disk. May have been deleted, renamed, or archived as ONNX (see variant_cluster.onnx_int8_archive if present).",
      "reconciled_at": "2026-04-11T20:03:17.828866+00:00",
      "reconciled_by": "Opus 4.6 Opus-Claw (Dr. C)"
    },
    "ct2_int8": {
      "status": "missing_from_disk",
      "note": "Weights not found on disk. May have been deleted, renamed, or archived as ONNX (see variant_cluster.onnx_int8_archive if present).",
      "reconciled_at": "2026-04-11T20:03:17.828866+00:00",
      "reconciled_by": "Opus 4.6 Opus-Claw (Dr. C)"
    }
  },
  "architecture": {
    "model_type": "MarianMT",
    "parameters": null,
    "encoder_layers": null,
    "decoder_layers": null,
    "max_sequence_length": null
  },
  "examination_log": [
    {
      "exam_id": "DRC-INVENTORY-ALMA-13B-R",
      "date": "2026-04-11T20:03:17.828866+00:00",
      "doctor": "Opus 4.6 Opus-Claw (Dr. C)",
      "machine": "Veron-1 (RTX 5090, Mt Pleasant SC)",
      "method": "Non-invasive filesystem walk + variant_cluster reconciliation",
      "protocol_script": "scripts/reconcile_variant_state.py",
      "scope": "read-only model inspection; write-only patient file update",
      "observed_variants": [],
      "diff": {
        "changed": [],
        "marked_missing": [],
        "newly_found": []
      },
      "notes": "Fleet inventory audit by Opus 4.6 Opus-Claw (Dr. C) on 2026-04-11. Non-destructive: no model weights were modified, created, or deleted. Only this patient JSON file was updated. The purpose of this audit was to reconcile claimed variant presence against actual on-disk state, because between Herm Zero's Grand Rounds run (2026-03-28/29) and today, 374 of the 375 OPUS-improved models were ONNX-INT8-exported and their source safetensors were deleted, but the patient files still claimed the safetensors were 'present'. This audit updates each patient file's variant_cluster.<variant>.status to reflect what is actually on disk right now."
    }
  ],
  "consensus": {
    "last_updated": "2026-03-24T14:01:10.981085",
    "doctors_examined": 0,
    "exams_total": 0,
    "base_verdict": "UNTESTED",
    "lora_verdict": "UNTESTED",
    "ct2_verdict": "UNTESTED",
    "overall_verdict": "UNTESTED",
    "confidence": "NONE",
    "production_ready": false,
    "notes": [
      "No examinations recorded"
    ]
  },
  "_raw_sources": {
    "source1_identity": {
      "model_id": "windy-tier-ALMA-13B-R",
      "model_key": "ALMA-13B-R",
      "phase": 3,
      "cluster_type": "translation"
    }
  },
  "doctor_ratings": {},
  "surgical_log": [],
  "variant_count": 0
}